ConfigRegistry.py
config_registry-1.0.0.dist-info/METADATA
config_registry-1.0.0.dist-info/WHEEL
config_registry-1.0.0.dist-info/top_level.txt
config_registry-1.0.0.dist-info/RECORD
