Metadata-Version: 2.1
Name: config-registry
Version: 1.0.0
Summary: python config registry package
Home-page: https://pypi.org/project/config-registry
Author: ZhangTianJie
Author-email: ztj1993@gmail.com
License: MIT License
Keywords: registry config json yaml
Platform: UNKNOWN
